{
    "NAME": "random_tsp-24-20-7",
    "TYPE": "TSPSD",
    "COMMENT": "24 random locations, 20 identical edges deleted for each location",
    "DIMENSION": 24,
    "EDGE_WEIGHT_TYPE": "EUC_2D",
    "NODE_COORDS": {
        "1": [
            21,
            99
        ],
        "2": [
            78,
            83
        ],
        "3": [
            52,
            81
        ],
        "4": [
            96,
            19
        ],
        "5": [
            64,
            95
        ],
        "6": [
            71,
            100
        ],
        "7": [
            12,
            48
        ],
        "8": [
            51,
            6
        ],
        "9": [
            52,
            22
        ],
        "10": [
            96,
            84
        ],
        "11": [
            71,
            9
        ],
        "12": [
            51,
            78
        ],
        "13": [
            15,
            55
        ],
        "14": [
            86,
            14
        ],
        "15": [
            14,
            87
        ],
        "16": [
            65,
            4
        ],
        "17": [
            61,
            56
        ],
        "18": [
            84,
            40
        ],
        "19": [
            0,
            27
        ],
        "20": [
            50,
            40
        ],
        "21": [
            28,
            75
        ],
        "22": [
            35,
            76
        ],
        "23": [
            94,
            11
        ],
        "24": [
            58,
            12
        ]
    },
    "DELETE": {
        "1": [
            [
                "9",
                "24"
            ],
            [
                "22",
                "24"
            ],
            [
                "10",
                "18"
            ],
            [
                "15",
                "23"
            ],
            [
                "5",
                "16"
            ],
            [
                "1",
                "11"
            ],
            [
                "7",
                "19"
            ],
            [
                "7",
                "14"
            ],
            [
                "7",
                "15"
            ],
            [
                "2",
                "3"
            ],
            [
                "10",
                "23"
            ],
            [
                "9",
                "11"
            ],
            [
                "10",
                "19"
            ],
            [
                "20",
                "22"
            ],
            [
                "20",
                "23"
            ],
            [
                "21",
                "23"
            ],
            [
                "5",
                "23"
            ],
            [
                "7",
                "12"
            ],
            [
                "18",
                "19"
            ],
            [
                "1",
                "6"
            ]
        ],
        "2": [
            [
                "9",
                "24"
            ],
            [
                "22",
                "24"
            ],
            [
                "10",
                "18"
            ],
            [
                "15",
                "23"
            ],
            [
                "5",
                "16"
            ],
            [
                "1",
                "11"
            ],
            [
                "7",
                "19"
            ],
            [
                "7",
                "14"
            ],
            [
                "7",
                "15"
            ],
            [
                "2",
                "3"
            ],
            [
                "10",
                "23"
            ],
            [
                "9",
                "11"
            ],
            [
                "10",
                "19"
            ],
            [
                "20",
                "22"
            ],
            [
                "20",
                "23"
            ],
            [
                "21",
                "23"
            ],
            [
                "5",
                "23"
            ],
            [
                "7",
                "12"
            ],
            [
                "18",
                "19"
            ],
            [
                "1",
                "6"
            ]
        ],
        "3": [
            [
                "9",
                "24"
            ],
            [
                "22",
                "24"
            ],
            [
                "10",
                "18"
            ],
            [
                "15",
                "23"
            ],
            [
                "5",
                "16"
            ],
            [
                "1",
                "11"
            ],
            [
                "7",
                "19"
            ],
            [
                "7",
                "14"
            ],
            [
                "7",
                "15"
            ],
            [
                "2",
                "3"
            ],
            [
                "10",
                "23"
            ],
            [
                "9",
                "11"
            ],
            [
                "10",
                "19"
            ],
            [
                "20",
                "22"
            ],
            [
                "20",
                "23"
            ],
            [
                "21",
                "23"
            ],
            [
                "5",
                "23"
            ],
            [
                "7",
                "12"
            ],
            [
                "18",
                "19"
            ],
            [
                "1",
                "6"
            ]
        ],
        "4": [
            [
                "9",
                "24"
            ],
            [
                "22",
                "24"
            ],
            [
                "10",
                "18"
            ],
            [
                "15",
                "23"
            ],
            [
                "5",
                "16"
            ],
            [
                "1",
                "11"
            ],
            [
                "7",
                "19"
            ],
            [
                "7",
                "14"
            ],
            [
                "7",
                "15"
            ],
            [
                "2",
                "3"
            ],
            [
                "10",
                "23"
            ],
            [
                "9",
                "11"
            ],
            [
                "10",
                "19"
            ],
            [
                "20",
                "22"
            ],
            [
                "20",
                "23"
            ],
            [
                "21",
                "23"
            ],
            [
                "5",
                "23"
            ],
            [
                "7",
                "12"
            ],
            [
                "18",
                "19"
            ],
            [
                "1",
                "6"
            ]
        ],
        "5": [
            [
                "9",
                "24"
            ],
            [
                "22",
                "24"
            ],
            [
                "10",
                "18"
            ],
            [
                "15",
                "23"
            ],
            [
                "5",
                "16"
            ],
            [
                "1",
                "11"
            ],
            [
                "7",
                "19"
            ],
            [
                "7",
                "14"
            ],
            [
                "7",
                "15"
            ],
            [
                "2",
                "3"
            ],
            [
                "10",
                "23"
            ],
            [
                "9",
                "11"
            ],
            [
                "10",
                "19"
            ],
            [
                "20",
                "22"
            ],
            [
                "20",
                "23"
            ],
            [
                "21",
                "23"
            ],
            [
                "5",
                "23"
            ],
            [
                "7",
                "12"
            ],
            [
                "18",
                "19"
            ],
            [
                "1",
                "6"
            ]
        ],
        "6": [
            [
                "9",
                "24"
            ],
            [
                "22",
                "24"
            ],
            [
                "10",
                "18"
            ],
            [
                "15",
                "23"
            ],
            [
                "5",
                "16"
            ],
            [
                "1",
                "11"
            ],
            [
                "7",
                "19"
            ],
            [
                "7",
                "14"
            ],
            [
                "7",
                "15"
            ],
            [
                "2",
                "3"
            ],
            [
                "10",
                "23"
            ],
            [
                "9",
                "11"
            ],
            [
                "10",
                "19"
            ],
            [
                "20",
                "22"
            ],
            [
                "20",
                "23"
            ],
            [
                "21",
                "23"
            ],
            [
                "5",
                "23"
            ],
            [
                "7",
                "12"
            ],
            [
                "18",
                "19"
            ],
            [
                "1",
                "6"
            ]
        ],
        "7": [
            [
                "9",
                "24"
            ],
            [
                "22",
                "24"
            ],
            [
                "10",
                "18"
            ],
            [
                "15",
                "23"
            ],
            [
                "5",
                "16"
            ],
            [
                "1",
                "11"
            ],
            [
                "7",
                "19"
            ],
            [
                "7",
                "14"
            ],
            [
                "7",
                "15"
            ],
            [
                "2",
                "3"
            ],
            [
                "10",
                "23"
            ],
            [
                "9",
                "11"
            ],
            [
                "10",
                "19"
            ],
            [
                "20",
                "22"
            ],
            [
                "20",
                "23"
            ],
            [
                "21",
                "23"
            ],
            [
                "5",
                "23"
            ],
            [
                "7",
                "12"
            ],
            [
                "18",
                "19"
            ],
            [
                "1",
                "6"
            ]
        ],
        "8": [
            [
                "9",
                "24"
            ],
            [
                "22",
                "24"
            ],
            [
                "10",
                "18"
            ],
            [
                "15",
                "23"
            ],
            [
                "5",
                "16"
            ],
            [
                "1",
                "11"
            ],
            [
                "7",
                "19"
            ],
            [
                "7",
                "14"
            ],
            [
                "7",
                "15"
            ],
            [
                "2",
                "3"
            ],
            [
                "10",
                "23"
            ],
            [
                "9",
                "11"
            ],
            [
                "10",
                "19"
            ],
            [
                "20",
                "22"
            ],
            [
                "20",
                "23"
            ],
            [
                "21",
                "23"
            ],
            [
                "5",
                "23"
            ],
            [
                "7",
                "12"
            ],
            [
                "18",
                "19"
            ],
            [
                "1",
                "6"
            ]
        ],
        "9": [
            [
                "9",
                "24"
            ],
            [
                "22",
                "24"
            ],
            [
                "10",
                "18"
            ],
            [
                "15",
                "23"
            ],
            [
                "5",
                "16"
            ],
            [
                "1",
                "11"
            ],
            [
                "7",
                "19"
            ],
            [
                "7",
                "14"
            ],
            [
                "7",
                "15"
            ],
            [
                "2",
                "3"
            ],
            [
                "10",
                "23"
            ],
            [
                "9",
                "11"
            ],
            [
                "10",
                "19"
            ],
            [
                "20",
                "22"
            ],
            [
                "20",
                "23"
            ],
            [
                "21",
                "23"
            ],
            [
                "5",
                "23"
            ],
            [
                "7",
                "12"
            ],
            [
                "18",
                "19"
            ],
            [
                "1",
                "6"
            ]
        ],
        "10": [
            [
                "9",
                "24"
            ],
            [
                "22",
                "24"
            ],
            [
                "10",
                "18"
            ],
            [
                "15",
                "23"
            ],
            [
                "5",
                "16"
            ],
            [
                "1",
                "11"
            ],
            [
                "7",
                "19"
            ],
            [
                "7",
                "14"
            ],
            [
                "7",
                "15"
            ],
            [
                "2",
                "3"
            ],
            [
                "10",
                "23"
            ],
            [
                "9",
                "11"
            ],
            [
                "10",
                "19"
            ],
            [
                "20",
                "22"
            ],
            [
                "20",
                "23"
            ],
            [
                "21",
                "23"
            ],
            [
                "5",
                "23"
            ],
            [
                "7",
                "12"
            ],
            [
                "18",
                "19"
            ],
            [
                "1",
                "6"
            ]
        ],
        "11": [
            [
                "9",
                "24"
            ],
            [
                "22",
                "24"
            ],
            [
                "10",
                "18"
            ],
            [
                "15",
                "23"
            ],
            [
                "5",
                "16"
            ],
            [
                "1",
                "11"
            ],
            [
                "7",
                "19"
            ],
            [
                "7",
                "14"
            ],
            [
                "7",
                "15"
            ],
            [
                "2",
                "3"
            ],
            [
                "10",
                "23"
            ],
            [
                "9",
                "11"
            ],
            [
                "10",
                "19"
            ],
            [
                "20",
                "22"
            ],
            [
                "20",
                "23"
            ],
            [
                "21",
                "23"
            ],
            [
                "5",
                "23"
            ],
            [
                "7",
                "12"
            ],
            [
                "18",
                "19"
            ],
            [
                "1",
                "6"
            ]
        ],
        "12": [
            [
                "9",
                "24"
            ],
            [
                "22",
                "24"
            ],
            [
                "10",
                "18"
            ],
            [
                "15",
                "23"
            ],
            [
                "5",
                "16"
            ],
            [
                "1",
                "11"
            ],
            [
                "7",
                "19"
            ],
            [
                "7",
                "14"
            ],
            [
                "7",
                "15"
            ],
            [
                "2",
                "3"
            ],
            [
                "10",
                "23"
            ],
            [
                "9",
                "11"
            ],
            [
                "10",
                "19"
            ],
            [
                "20",
                "22"
            ],
            [
                "20",
                "23"
            ],
            [
                "21",
                "23"
            ],
            [
                "5",
                "23"
            ],
            [
                "7",
                "12"
            ],
            [
                "18",
                "19"
            ],
            [
                "1",
                "6"
            ]
        ],
        "13": [
            [
                "9",
                "24"
            ],
            [
                "22",
                "24"
            ],
            [
                "10",
                "18"
            ],
            [
                "15",
                "23"
            ],
            [
                "5",
                "16"
            ],
            [
                "1",
                "11"
            ],
            [
                "7",
                "19"
            ],
            [
                "7",
                "14"
            ],
            [
                "7",
                "15"
            ],
            [
                "2",
                "3"
            ],
            [
                "10",
                "23"
            ],
            [
                "9",
                "11"
            ],
            [
                "10",
                "19"
            ],
            [
                "20",
                "22"
            ],
            [
                "20",
                "23"
            ],
            [
                "21",
                "23"
            ],
            [
                "5",
                "23"
            ],
            [
                "7",
                "12"
            ],
            [
                "18",
                "19"
            ],
            [
                "1",
                "6"
            ]
        ],
        "14": [
            [
                "9",
                "24"
            ],
            [
                "22",
                "24"
            ],
            [
                "10",
                "18"
            ],
            [
                "15",
                "23"
            ],
            [
                "5",
                "16"
            ],
            [
                "1",
                "11"
            ],
            [
                "7",
                "19"
            ],
            [
                "7",
                "14"
            ],
            [
                "7",
                "15"
            ],
            [
                "2",
                "3"
            ],
            [
                "10",
                "23"
            ],
            [
                "9",
                "11"
            ],
            [
                "10",
                "19"
            ],
            [
                "20",
                "22"
            ],
            [
                "20",
                "23"
            ],
            [
                "21",
                "23"
            ],
            [
                "5",
                "23"
            ],
            [
                "7",
                "12"
            ],
            [
                "18",
                "19"
            ],
            [
                "1",
                "6"
            ]
        ],
        "15": [
            [
                "9",
                "24"
            ],
            [
                "22",
                "24"
            ],
            [
                "10",
                "18"
            ],
            [
                "15",
                "23"
            ],
            [
                "5",
                "16"
            ],
            [
                "1",
                "11"
            ],
            [
                "7",
                "19"
            ],
            [
                "7",
                "14"
            ],
            [
                "7",
                "15"
            ],
            [
                "2",
                "3"
            ],
            [
                "10",
                "23"
            ],
            [
                "9",
                "11"
            ],
            [
                "10",
                "19"
            ],
            [
                "20",
                "22"
            ],
            [
                "20",
                "23"
            ],
            [
                "21",
                "23"
            ],
            [
                "5",
                "23"
            ],
            [
                "7",
                "12"
            ],
            [
                "18",
                "19"
            ],
            [
                "1",
                "6"
            ]
        ],
        "16": [
            [
                "9",
                "24"
            ],
            [
                "22",
                "24"
            ],
            [
                "10",
                "18"
            ],
            [
                "15",
                "23"
            ],
            [
                "5",
                "16"
            ],
            [
                "1",
                "11"
            ],
            [
                "7",
                "19"
            ],
            [
                "7",
                "14"
            ],
            [
                "7",
                "15"
            ],
            [
                "2",
                "3"
            ],
            [
                "10",
                "23"
            ],
            [
                "9",
                "11"
            ],
            [
                "10",
                "19"
            ],
            [
                "20",
                "22"
            ],
            [
                "20",
                "23"
            ],
            [
                "21",
                "23"
            ],
            [
                "5",
                "23"
            ],
            [
                "7",
                "12"
            ],
            [
                "18",
                "19"
            ],
            [
                "1",
                "6"
            ]
        ],
        "17": [
            [
                "9",
                "24"
            ],
            [
                "22",
                "24"
            ],
            [
                "10",
                "18"
            ],
            [
                "15",
                "23"
            ],
            [
                "5",
                "16"
            ],
            [
                "1",
                "11"
            ],
            [
                "7",
                "19"
            ],
            [
                "7",
                "14"
            ],
            [
                "7",
                "15"
            ],
            [
                "2",
                "3"
            ],
            [
                "10",
                "23"
            ],
            [
                "9",
                "11"
            ],
            [
                "10",
                "19"
            ],
            [
                "20",
                "22"
            ],
            [
                "20",
                "23"
            ],
            [
                "21",
                "23"
            ],
            [
                "5",
                "23"
            ],
            [
                "7",
                "12"
            ],
            [
                "18",
                "19"
            ],
            [
                "1",
                "6"
            ]
        ],
        "18": [
            [
                "9",
                "24"
            ],
            [
                "22",
                "24"
            ],
            [
                "10",
                "18"
            ],
            [
                "15",
                "23"
            ],
            [
                "5",
                "16"
            ],
            [
                "1",
                "11"
            ],
            [
                "7",
                "19"
            ],
            [
                "7",
                "14"
            ],
            [
                "7",
                "15"
            ],
            [
                "2",
                "3"
            ],
            [
                "10",
                "23"
            ],
            [
                "9",
                "11"
            ],
            [
                "10",
                "19"
            ],
            [
                "20",
                "22"
            ],
            [
                "20",
                "23"
            ],
            [
                "21",
                "23"
            ],
            [
                "5",
                "23"
            ],
            [
                "7",
                "12"
            ],
            [
                "18",
                "19"
            ],
            [
                "1",
                "6"
            ]
        ],
        "19": [
            [
                "9",
                "24"
            ],
            [
                "22",
                "24"
            ],
            [
                "10",
                "18"
            ],
            [
                "15",
                "23"
            ],
            [
                "5",
                "16"
            ],
            [
                "1",
                "11"
            ],
            [
                "7",
                "19"
            ],
            [
                "7",
                "14"
            ],
            [
                "7",
                "15"
            ],
            [
                "2",
                "3"
            ],
            [
                "10",
                "23"
            ],
            [
                "9",
                "11"
            ],
            [
                "10",
                "19"
            ],
            [
                "20",
                "22"
            ],
            [
                "20",
                "23"
            ],
            [
                "21",
                "23"
            ],
            [
                "5",
                "23"
            ],
            [
                "7",
                "12"
            ],
            [
                "18",
                "19"
            ],
            [
                "1",
                "6"
            ]
        ],
        "20": [
            [
                "9",
                "24"
            ],
            [
                "22",
                "24"
            ],
            [
                "10",
                "18"
            ],
            [
                "15",
                "23"
            ],
            [
                "5",
                "16"
            ],
            [
                "1",
                "11"
            ],
            [
                "7",
                "19"
            ],
            [
                "7",
                "14"
            ],
            [
                "7",
                "15"
            ],
            [
                "2",
                "3"
            ],
            [
                "10",
                "23"
            ],
            [
                "9",
                "11"
            ],
            [
                "10",
                "19"
            ],
            [
                "20",
                "22"
            ],
            [
                "20",
                "23"
            ],
            [
                "21",
                "23"
            ],
            [
                "5",
                "23"
            ],
            [
                "7",
                "12"
            ],
            [
                "18",
                "19"
            ],
            [
                "1",
                "6"
            ]
        ],
        "21": [
            [
                "9",
                "24"
            ],
            [
                "22",
                "24"
            ],
            [
                "10",
                "18"
            ],
            [
                "15",
                "23"
            ],
            [
                "5",
                "16"
            ],
            [
                "1",
                "11"
            ],
            [
                "7",
                "19"
            ],
            [
                "7",
                "14"
            ],
            [
                "7",
                "15"
            ],
            [
                "2",
                "3"
            ],
            [
                "10",
                "23"
            ],
            [
                "9",
                "11"
            ],
            [
                "10",
                "19"
            ],
            [
                "20",
                "22"
            ],
            [
                "20",
                "23"
            ],
            [
                "21",
                "23"
            ],
            [
                "5",
                "23"
            ],
            [
                "7",
                "12"
            ],
            [
                "18",
                "19"
            ],
            [
                "1",
                "6"
            ]
        ],
        "22": [
            [
                "9",
                "24"
            ],
            [
                "22",
                "24"
            ],
            [
                "10",
                "18"
            ],
            [
                "15",
                "23"
            ],
            [
                "5",
                "16"
            ],
            [
                "1",
                "11"
            ],
            [
                "7",
                "19"
            ],
            [
                "7",
                "14"
            ],
            [
                "7",
                "15"
            ],
            [
                "2",
                "3"
            ],
            [
                "10",
                "23"
            ],
            [
                "9",
                "11"
            ],
            [
                "10",
                "19"
            ],
            [
                "20",
                "22"
            ],
            [
                "20",
                "23"
            ],
            [
                "21",
                "23"
            ],
            [
                "5",
                "23"
            ],
            [
                "7",
                "12"
            ],
            [
                "18",
                "19"
            ],
            [
                "1",
                "6"
            ]
        ],
        "23": [
            [
                "9",
                "24"
            ],
            [
                "22",
                "24"
            ],
            [
                "10",
                "18"
            ],
            [
                "15",
                "23"
            ],
            [
                "5",
                "16"
            ],
            [
                "1",
                "11"
            ],
            [
                "7",
                "19"
            ],
            [
                "7",
                "14"
            ],
            [
                "7",
                "15"
            ],
            [
                "2",
                "3"
            ],
            [
                "10",
                "23"
            ],
            [
                "9",
                "11"
            ],
            [
                "10",
                "19"
            ],
            [
                "20",
                "22"
            ],
            [
                "20",
                "23"
            ],
            [
                "21",
                "23"
            ],
            [
                "5",
                "23"
            ],
            [
                "7",
                "12"
            ],
            [
                "18",
                "19"
            ],
            [
                "1",
                "6"
            ]
        ],
        "24": [
            [
                "9",
                "24"
            ],
            [
                "22",
                "24"
            ],
            [
                "10",
                "18"
            ],
            [
                "15",
                "23"
            ],
            [
                "5",
                "16"
            ],
            [
                "1",
                "11"
            ],
            [
                "7",
                "19"
            ],
            [
                "7",
                "14"
            ],
            [
                "7",
                "15"
            ],
            [
                "2",
                "3"
            ],
            [
                "10",
                "23"
            ],
            [
                "9",
                "11"
            ],
            [
                "10",
                "19"
            ],
            [
                "20",
                "22"
            ],
            [
                "20",
                "23"
            ],
            [
                "21",
                "23"
            ],
            [
                "5",
                "23"
            ],
            [
                "7",
                "12"
            ],
            [
                "18",
                "19"
            ],
            [
                "1",
                "6"
            ]
        ]
    }
}