{
    "NAME": "random_tsp-24-49-16",
    "TYPE": "TSPSD",
    "COMMENT": "24 random locations, 49 identical edges deleted for each location",
    "DIMENSION": 24,
    "EDGE_WEIGHT_TYPE": "EUC_2D",
    "NODE_COORDS": {
        "1": [
            39,
            47
        ],
        "2": [
            48,
            39
        ],
        "3": [
            11,
            13
        ],
        "4": [
            63,
            40
        ],
        "5": [
            69,
            92
        ],
        "6": [
            93,
            78
        ],
        "7": [
            20,
            29
        ],
        "8": [
            45,
            83
        ],
        "9": [
            1,
            83
        ],
        "10": [
            17,
            36
        ],
        "11": [
            16,
            75
        ],
        "12": [
            0,
            91
        ],
        "13": [
            85,
            26
        ],
        "14": [
            74,
            2
        ],
        "15": [
            48,
            80
        ],
        "16": [
            19,
            36
        ],
        "17": [
            17,
            27
        ],
        "18": [
            88,
            80
        ],
        "19": [
            17,
            67
        ],
        "20": [
            4,
            69
        ],
        "21": [
            81,
            41
        ],
        "22": [
            12,
            68
        ],
        "23": [
            36,
            1
        ],
        "24": [
            41,
            42
        ]
    },
    "DELETE": {
        "1": [
            [
                "2",
                "4"
            ],
            [
                "2",
                "13"
            ],
            [
                "2",
                "15"
            ],
            [
                "7",
                "13"
            ],
            [
                "1",
                "10"
            ],
            [
                "1",
                "19"
            ],
            [
                "4",
                "6"
            ],
            [
                "3",
                "7"
            ],
            [
                "8",
                "18"
            ],
            [
                "1",
                "12"
            ],
            [
                "22",
                "23"
            ],
            [
                "7",
                "23"
            ],
            [
                "5",
                "17"
            ],
            [
                "16",
                "24"
            ],
            [
                "5",
                "22"
            ],
            [
                "12",
                "16"
            ],
            [
                "6",
                "17"
            ],
            [
                "7",
                "18"
            ],
            [
                "8",
                "21"
            ],
            [
                "13",
                "14"
            ],
            [
                "11",
                "19"
            ],
            [
                "12",
                "20"
            ],
            [
                "3",
                "15"
            ],
            [
                "1",
                "11"
            ],
            [
                "5",
                "18"
            ],
            [
                "18",
                "19"
            ],
            [
                "6",
                "13"
            ],
            [
                "19",
                "21"
            ],
            [
                "3",
                "6"
            ],
            [
                "2",
                "7"
            ],
            [
                "2",
                "20"
            ],
            [
                "4",
                "16"
            ],
            [
                "9",
                "24"
            ],
            [
                "12",
                "15"
            ],
            [
                "1",
                "16"
            ],
            [
                "10",
                "17"
            ],
            [
                "11",
                "12"
            ],
            [
                "14",
                "17"
            ],
            [
                "23",
                "24"
            ],
            [
                "11",
                "21"
            ],
            [
                "2",
                "14"
            ],
            [
                "9",
                "19"
            ],
            [
                "2",
                "6"
            ],
            [
                "4",
                "22"
            ],
            [
                "4",
                "14"
            ],
            [
                "5",
                "14"
            ],
            [
                "17",
                "18"
            ],
            [
                "6",
                "20"
            ],
            [
                "18",
                "24"
            ]
        ],
        "2": [
            [
                "2",
                "4"
            ],
            [
                "2",
                "13"
            ],
            [
                "2",
                "15"
            ],
            [
                "7",
                "13"
            ],
            [
                "1",
                "10"
            ],
            [
                "1",
                "19"
            ],
            [
                "4",
                "6"
            ],
            [
                "3",
                "7"
            ],
            [
                "8",
                "18"
            ],
            [
                "1",
                "12"
            ],
            [
                "22",
                "23"
            ],
            [
                "7",
                "23"
            ],
            [
                "5",
                "17"
            ],
            [
                "16",
                "24"
            ],
            [
                "5",
                "22"
            ],
            [
                "12",
                "16"
            ],
            [
                "6",
                "17"
            ],
            [
                "7",
                "18"
            ],
            [
                "8",
                "21"
            ],
            [
                "13",
                "14"
            ],
            [
                "11",
                "19"
            ],
            [
                "12",
                "20"
            ],
            [
                "3",
                "15"
            ],
            [
                "1",
                "11"
            ],
            [
                "5",
                "18"
            ],
            [
                "18",
                "19"
            ],
            [
                "6",
                "13"
            ],
            [
                "19",
                "21"
            ],
            [
                "3",
                "6"
            ],
            [
                "2",
                "7"
            ],
            [
                "2",
                "20"
            ],
            [
                "4",
                "16"
            ],
            [
                "9",
                "24"
            ],
            [
                "12",
                "15"
            ],
            [
                "1",
                "16"
            ],
            [
                "10",
                "17"
            ],
            [
                "11",
                "12"
            ],
            [
                "14",
                "17"
            ],
            [
                "23",
                "24"
            ],
            [
                "11",
                "21"
            ],
            [
                "2",
                "14"
            ],
            [
                "9",
                "19"
            ],
            [
                "2",
                "6"
            ],
            [
                "4",
                "22"
            ],
            [
                "4",
                "14"
            ],
            [
                "5",
                "14"
            ],
            [
                "17",
                "18"
            ],
            [
                "6",
                "20"
            ],
            [
                "18",
                "24"
            ]
        ],
        "3": [
            [
                "2",
                "4"
            ],
            [
                "2",
                "13"
            ],
            [
                "2",
                "15"
            ],
            [
                "7",
                "13"
            ],
            [
                "1",
                "10"
            ],
            [
                "1",
                "19"
            ],
            [
                "4",
                "6"
            ],
            [
                "3",
                "7"
            ],
            [
                "8",
                "18"
            ],
            [
                "1",
                "12"
            ],
            [
                "22",
                "23"
            ],
            [
                "7",
                "23"
            ],
            [
                "5",
                "17"
            ],
            [
                "16",
                "24"
            ],
            [
                "5",
                "22"
            ],
            [
                "12",
                "16"
            ],
            [
                "6",
                "17"
            ],
            [
                "7",
                "18"
            ],
            [
                "8",
                "21"
            ],
            [
                "13",
                "14"
            ],
            [
                "11",
                "19"
            ],
            [
                "12",
                "20"
            ],
            [
                "3",
                "15"
            ],
            [
                "1",
                "11"
            ],
            [
                "5",
                "18"
            ],
            [
                "18",
                "19"
            ],
            [
                "6",
                "13"
            ],
            [
                "19",
                "21"
            ],
            [
                "3",
                "6"
            ],
            [
                "2",
                "7"
            ],
            [
                "2",
                "20"
            ],
            [
                "4",
                "16"
            ],
            [
                "9",
                "24"
            ],
            [
                "12",
                "15"
            ],
            [
                "1",
                "16"
            ],
            [
                "10",
                "17"
            ],
            [
                "11",
                "12"
            ],
            [
                "14",
                "17"
            ],
            [
                "23",
                "24"
            ],
            [
                "11",
                "21"
            ],
            [
                "2",
                "14"
            ],
            [
                "9",
                "19"
            ],
            [
                "2",
                "6"
            ],
            [
                "4",
                "22"
            ],
            [
                "4",
                "14"
            ],
            [
                "5",
                "14"
            ],
            [
                "17",
                "18"
            ],
            [
                "6",
                "20"
            ],
            [
                "18",
                "24"
            ]
        ],
        "4": [
            [
                "2",
                "4"
            ],
            [
                "2",
                "13"
            ],
            [
                "2",
                "15"
            ],
            [
                "7",
                "13"
            ],
            [
                "1",
                "10"
            ],
            [
                "1",
                "19"
            ],
            [
                "4",
                "6"
            ],
            [
                "3",
                "7"
            ],
            [
                "8",
                "18"
            ],
            [
                "1",
                "12"
            ],
            [
                "22",
                "23"
            ],
            [
                "7",
                "23"
            ],
            [
                "5",
                "17"
            ],
            [
                "16",
                "24"
            ],
            [
                "5",
                "22"
            ],
            [
                "12",
                "16"
            ],
            [
                "6",
                "17"
            ],
            [
                "7",
                "18"
            ],
            [
                "8",
                "21"
            ],
            [
                "13",
                "14"
            ],
            [
                "11",
                "19"
            ],
            [
                "12",
                "20"
            ],
            [
                "3",
                "15"
            ],
            [
                "1",
                "11"
            ],
            [
                "5",
                "18"
            ],
            [
                "18",
                "19"
            ],
            [
                "6",
                "13"
            ],
            [
                "19",
                "21"
            ],
            [
                "3",
                "6"
            ],
            [
                "2",
                "7"
            ],
            [
                "2",
                "20"
            ],
            [
                "4",
                "16"
            ],
            [
                "9",
                "24"
            ],
            [
                "12",
                "15"
            ],
            [
                "1",
                "16"
            ],
            [
                "10",
                "17"
            ],
            [
                "11",
                "12"
            ],
            [
                "14",
                "17"
            ],
            [
                "23",
                "24"
            ],
            [
                "11",
                "21"
            ],
            [
                "2",
                "14"
            ],
            [
                "9",
                "19"
            ],
            [
                "2",
                "6"
            ],
            [
                "4",
                "22"
            ],
            [
                "4",
                "14"
            ],
            [
                "5",
                "14"
            ],
            [
                "17",
                "18"
            ],
            [
                "6",
                "20"
            ],
            [
                "18",
                "24"
            ]
        ],
        "5": [
            [
                "2",
                "4"
            ],
            [
                "2",
                "13"
            ],
            [
                "2",
                "15"
            ],
            [
                "7",
                "13"
            ],
            [
                "1",
                "10"
            ],
            [
                "1",
                "19"
            ],
            [
                "4",
                "6"
            ],
            [
                "3",
                "7"
            ],
            [
                "8",
                "18"
            ],
            [
                "1",
                "12"
            ],
            [
                "22",
                "23"
            ],
            [
                "7",
                "23"
            ],
            [
                "5",
                "17"
            ],
            [
                "16",
                "24"
            ],
            [
                "5",
                "22"
            ],
            [
                "12",
                "16"
            ],
            [
                "6",
                "17"
            ],
            [
                "7",
                "18"
            ],
            [
                "8",
                "21"
            ],
            [
                "13",
                "14"
            ],
            [
                "11",
                "19"
            ],
            [
                "12",
                "20"
            ],
            [
                "3",
                "15"
            ],
            [
                "1",
                "11"
            ],
            [
                "5",
                "18"
            ],
            [
                "18",
                "19"
            ],
            [
                "6",
                "13"
            ],
            [
                "19",
                "21"
            ],
            [
                "3",
                "6"
            ],
            [
                "2",
                "7"
            ],
            [
                "2",
                "20"
            ],
            [
                "4",
                "16"
            ],
            [
                "9",
                "24"
            ],
            [
                "12",
                "15"
            ],
            [
                "1",
                "16"
            ],
            [
                "10",
                "17"
            ],
            [
                "11",
                "12"
            ],
            [
                "14",
                "17"
            ],
            [
                "23",
                "24"
            ],
            [
                "11",
                "21"
            ],
            [
                "2",
                "14"
            ],
            [
                "9",
                "19"
            ],
            [
                "2",
                "6"
            ],
            [
                "4",
                "22"
            ],
            [
                "4",
                "14"
            ],
            [
                "5",
                "14"
            ],
            [
                "17",
                "18"
            ],
            [
                "6",
                "20"
            ],
            [
                "18",
                "24"
            ]
        ],
        "6": [
            [
                "2",
                "4"
            ],
            [
                "2",
                "13"
            ],
            [
                "2",
                "15"
            ],
            [
                "7",
                "13"
            ],
            [
                "1",
                "10"
            ],
            [
                "1",
                "19"
            ],
            [
                "4",
                "6"
            ],
            [
                "3",
                "7"
            ],
            [
                "8",
                "18"
            ],
            [
                "1",
                "12"
            ],
            [
                "22",
                "23"
            ],
            [
                "7",
                "23"
            ],
            [
                "5",
                "17"
            ],
            [
                "16",
                "24"
            ],
            [
                "5",
                "22"
            ],
            [
                "12",
                "16"
            ],
            [
                "6",
                "17"
            ],
            [
                "7",
                "18"
            ],
            [
                "8",
                "21"
            ],
            [
                "13",
                "14"
            ],
            [
                "11",
                "19"
            ],
            [
                "12",
                "20"
            ],
            [
                "3",
                "15"
            ],
            [
                "1",
                "11"
            ],
            [
                "5",
                "18"
            ],
            [
                "18",
                "19"
            ],
            [
                "6",
                "13"
            ],
            [
                "19",
                "21"
            ],
            [
                "3",
                "6"
            ],
            [
                "2",
                "7"
            ],
            [
                "2",
                "20"
            ],
            [
                "4",
                "16"
            ],
            [
                "9",
                "24"
            ],
            [
                "12",
                "15"
            ],
            [
                "1",
                "16"
            ],
            [
                "10",
                "17"
            ],
            [
                "11",
                "12"
            ],
            [
                "14",
                "17"
            ],
            [
                "23",
                "24"
            ],
            [
                "11",
                "21"
            ],
            [
                "2",
                "14"
            ],
            [
                "9",
                "19"
            ],
            [
                "2",
                "6"
            ],
            [
                "4",
                "22"
            ],
            [
                "4",
                "14"
            ],
            [
                "5",
                "14"
            ],
            [
                "17",
                "18"
            ],
            [
                "6",
                "20"
            ],
            [
                "18",
                "24"
            ]
        ],
        "7": [
            [
                "2",
                "4"
            ],
            [
                "2",
                "13"
            ],
            [
                "2",
                "15"
            ],
            [
                "7",
                "13"
            ],
            [
                "1",
                "10"
            ],
            [
                "1",
                "19"
            ],
            [
                "4",
                "6"
            ],
            [
                "3",
                "7"
            ],
            [
                "8",
                "18"
            ],
            [
                "1",
                "12"
            ],
            [
                "22",
                "23"
            ],
            [
                "7",
                "23"
            ],
            [
                "5",
                "17"
            ],
            [
                "16",
                "24"
            ],
            [
                "5",
                "22"
            ],
            [
                "12",
                "16"
            ],
            [
                "6",
                "17"
            ],
            [
                "7",
                "18"
            ],
            [
                "8",
                "21"
            ],
            [
                "13",
                "14"
            ],
            [
                "11",
                "19"
            ],
            [
                "12",
                "20"
            ],
            [
                "3",
                "15"
            ],
            [
                "1",
                "11"
            ],
            [
                "5",
                "18"
            ],
            [
                "18",
                "19"
            ],
            [
                "6",
                "13"
            ],
            [
                "19",
                "21"
            ],
            [
                "3",
                "6"
            ],
            [
                "2",
                "7"
            ],
            [
                "2",
                "20"
            ],
            [
                "4",
                "16"
            ],
            [
                "9",
                "24"
            ],
            [
                "12",
                "15"
            ],
            [
                "1",
                "16"
            ],
            [
                "10",
                "17"
            ],
            [
                "11",
                "12"
            ],
            [
                "14",
                "17"
            ],
            [
                "23",
                "24"
            ],
            [
                "11",
                "21"
            ],
            [
                "2",
                "14"
            ],
            [
                "9",
                "19"
            ],
            [
                "2",
                "6"
            ],
            [
                "4",
                "22"
            ],
            [
                "4",
                "14"
            ],
            [
                "5",
                "14"
            ],
            [
                "17",
                "18"
            ],
            [
                "6",
                "20"
            ],
            [
                "18",
                "24"
            ]
        ],
        "8": [
            [
                "2",
                "4"
            ],
            [
                "2",
                "13"
            ],
            [
                "2",
                "15"
            ],
            [
                "7",
                "13"
            ],
            [
                "1",
                "10"
            ],
            [
                "1",
                "19"
            ],
            [
                "4",
                "6"
            ],
            [
                "3",
                "7"
            ],
            [
                "8",
                "18"
            ],
            [
                "1",
                "12"
            ],
            [
                "22",
                "23"
            ],
            [
                "7",
                "23"
            ],
            [
                "5",
                "17"
            ],
            [
                "16",
                "24"
            ],
            [
                "5",
                "22"
            ],
            [
                "12",
                "16"
            ],
            [
                "6",
                "17"
            ],
            [
                "7",
                "18"
            ],
            [
                "8",
                "21"
            ],
            [
                "13",
                "14"
            ],
            [
                "11",
                "19"
            ],
            [
                "12",
                "20"
            ],
            [
                "3",
                "15"
            ],
            [
                "1",
                "11"
            ],
            [
                "5",
                "18"
            ],
            [
                "18",
                "19"
            ],
            [
                "6",
                "13"
            ],
            [
                "19",
                "21"
            ],
            [
                "3",
                "6"
            ],
            [
                "2",
                "7"
            ],
            [
                "2",
                "20"
            ],
            [
                "4",
                "16"
            ],
            [
                "9",
                "24"
            ],
            [
                "12",
                "15"
            ],
            [
                "1",
                "16"
            ],
            [
                "10",
                "17"
            ],
            [
                "11",
                "12"
            ],
            [
                "14",
                "17"
            ],
            [
                "23",
                "24"
            ],
            [
                "11",
                "21"
            ],
            [
                "2",
                "14"
            ],
            [
                "9",
                "19"
            ],
            [
                "2",
                "6"
            ],
            [
                "4",
                "22"
            ],
            [
                "4",
                "14"
            ],
            [
                "5",
                "14"
            ],
            [
                "17",
                "18"
            ],
            [
                "6",
                "20"
            ],
            [
                "18",
                "24"
            ]
        ],
        "9": [
            [
                "2",
                "4"
            ],
            [
                "2",
                "13"
            ],
            [
                "2",
                "15"
            ],
            [
                "7",
                "13"
            ],
            [
                "1",
                "10"
            ],
            [
                "1",
                "19"
            ],
            [
                "4",
                "6"
            ],
            [
                "3",
                "7"
            ],
            [
                "8",
                "18"
            ],
            [
                "1",
                "12"
            ],
            [
                "22",
                "23"
            ],
            [
                "7",
                "23"
            ],
            [
                "5",
                "17"
            ],
            [
                "16",
                "24"
            ],
            [
                "5",
                "22"
            ],
            [
                "12",
                "16"
            ],
            [
                "6",
                "17"
            ],
            [
                "7",
                "18"
            ],
            [
                "8",
                "21"
            ],
            [
                "13",
                "14"
            ],
            [
                "11",
                "19"
            ],
            [
                "12",
                "20"
            ],
            [
                "3",
                "15"
            ],
            [
                "1",
                "11"
            ],
            [
                "5",
                "18"
            ],
            [
                "18",
                "19"
            ],
            [
                "6",
                "13"
            ],
            [
                "19",
                "21"
            ],
            [
                "3",
                "6"
            ],
            [
                "2",
                "7"
            ],
            [
                "2",
                "20"
            ],
            [
                "4",
                "16"
            ],
            [
                "9",
                "24"
            ],
            [
                "12",
                "15"
            ],
            [
                "1",
                "16"
            ],
            [
                "10",
                "17"
            ],
            [
                "11",
                "12"
            ],
            [
                "14",
                "17"
            ],
            [
                "23",
                "24"
            ],
            [
                "11",
                "21"
            ],
            [
                "2",
                "14"
            ],
            [
                "9",
                "19"
            ],
            [
                "2",
                "6"
            ],
            [
                "4",
                "22"
            ],
            [
                "4",
                "14"
            ],
            [
                "5",
                "14"
            ],
            [
                "17",
                "18"
            ],
            [
                "6",
                "20"
            ],
            [
                "18",
                "24"
            ]
        ],
        "10": [
            [
                "2",
                "4"
            ],
            [
                "2",
                "13"
            ],
            [
                "2",
                "15"
            ],
            [
                "7",
                "13"
            ],
            [
                "1",
                "10"
            ],
            [
                "1",
                "19"
            ],
            [
                "4",
                "6"
            ],
            [
                "3",
                "7"
            ],
            [
                "8",
                "18"
            ],
            [
                "1",
                "12"
            ],
            [
                "22",
                "23"
            ],
            [
                "7",
                "23"
            ],
            [
                "5",
                "17"
            ],
            [
                "16",
                "24"
            ],
            [
                "5",
                "22"
            ],
            [
                "12",
                "16"
            ],
            [
                "6",
                "17"
            ],
            [
                "7",
                "18"
            ],
            [
                "8",
                "21"
            ],
            [
                "13",
                "14"
            ],
            [
                "11",
                "19"
            ],
            [
                "12",
                "20"
            ],
            [
                "3",
                "15"
            ],
            [
                "1",
                "11"
            ],
            [
                "5",
                "18"
            ],
            [
                "18",
                "19"
            ],
            [
                "6",
                "13"
            ],
            [
                "19",
                "21"
            ],
            [
                "3",
                "6"
            ],
            [
                "2",
                "7"
            ],
            [
                "2",
                "20"
            ],
            [
                "4",
                "16"
            ],
            [
                "9",
                "24"
            ],
            [
                "12",
                "15"
            ],
            [
                "1",
                "16"
            ],
            [
                "10",
                "17"
            ],
            [
                "11",
                "12"
            ],
            [
                "14",
                "17"
            ],
            [
                "23",
                "24"
            ],
            [
                "11",
                "21"
            ],
            [
                "2",
                "14"
            ],
            [
                "9",
                "19"
            ],
            [
                "2",
                "6"
            ],
            [
                "4",
                "22"
            ],
            [
                "4",
                "14"
            ],
            [
                "5",
                "14"
            ],
            [
                "17",
                "18"
            ],
            [
                "6",
                "20"
            ],
            [
                "18",
                "24"
            ]
        ],
        "11": [
            [
                "2",
                "4"
            ],
            [
                "2",
                "13"
            ],
            [
                "2",
                "15"
            ],
            [
                "7",
                "13"
            ],
            [
                "1",
                "10"
            ],
            [
                "1",
                "19"
            ],
            [
                "4",
                "6"
            ],
            [
                "3",
                "7"
            ],
            [
                "8",
                "18"
            ],
            [
                "1",
                "12"
            ],
            [
                "22",
                "23"
            ],
            [
                "7",
                "23"
            ],
            [
                "5",
                "17"
            ],
            [
                "16",
                "24"
            ],
            [
                "5",
                "22"
            ],
            [
                "12",
                "16"
            ],
            [
                "6",
                "17"
            ],
            [
                "7",
                "18"
            ],
            [
                "8",
                "21"
            ],
            [
                "13",
                "14"
            ],
            [
                "11",
                "19"
            ],
            [
                "12",
                "20"
            ],
            [
                "3",
                "15"
            ],
            [
                "1",
                "11"
            ],
            [
                "5",
                "18"
            ],
            [
                "18",
                "19"
            ],
            [
                "6",
                "13"
            ],
            [
                "19",
                "21"
            ],
            [
                "3",
                "6"
            ],
            [
                "2",
                "7"
            ],
            [
                "2",
                "20"
            ],
            [
                "4",
                "16"
            ],
            [
                "9",
                "24"
            ],
            [
                "12",
                "15"
            ],
            [
                "1",
                "16"
            ],
            [
                "10",
                "17"
            ],
            [
                "11",
                "12"
            ],
            [
                "14",
                "17"
            ],
            [
                "23",
                "24"
            ],
            [
                "11",
                "21"
            ],
            [
                "2",
                "14"
            ],
            [
                "9",
                "19"
            ],
            [
                "2",
                "6"
            ],
            [
                "4",
                "22"
            ],
            [
                "4",
                "14"
            ],
            [
                "5",
                "14"
            ],
            [
                "17",
                "18"
            ],
            [
                "6",
                "20"
            ],
            [
                "18",
                "24"
            ]
        ],
        "12": [
            [
                "2",
                "4"
            ],
            [
                "2",
                "13"
            ],
            [
                "2",
                "15"
            ],
            [
                "7",
                "13"
            ],
            [
                "1",
                "10"
            ],
            [
                "1",
                "19"
            ],
            [
                "4",
                "6"
            ],
            [
                "3",
                "7"
            ],
            [
                "8",
                "18"
            ],
            [
                "1",
                "12"
            ],
            [
                "22",
                "23"
            ],
            [
                "7",
                "23"
            ],
            [
                "5",
                "17"
            ],
            [
                "16",
                "24"
            ],
            [
                "5",
                "22"
            ],
            [
                "12",
                "16"
            ],
            [
                "6",
                "17"
            ],
            [
                "7",
                "18"
            ],
            [
                "8",
                "21"
            ],
            [
                "13",
                "14"
            ],
            [
                "11",
                "19"
            ],
            [
                "12",
                "20"
            ],
            [
                "3",
                "15"
            ],
            [
                "1",
                "11"
            ],
            [
                "5",
                "18"
            ],
            [
                "18",
                "19"
            ],
            [
                "6",
                "13"
            ],
            [
                "19",
                "21"
            ],
            [
                "3",
                "6"
            ],
            [
                "2",
                "7"
            ],
            [
                "2",
                "20"
            ],
            [
                "4",
                "16"
            ],
            [
                "9",
                "24"
            ],
            [
                "12",
                "15"
            ],
            [
                "1",
                "16"
            ],
            [
                "10",
                "17"
            ],
            [
                "11",
                "12"
            ],
            [
                "14",
                "17"
            ],
            [
                "23",
                "24"
            ],
            [
                "11",
                "21"
            ],
            [
                "2",
                "14"
            ],
            [
                "9",
                "19"
            ],
            [
                "2",
                "6"
            ],
            [
                "4",
                "22"
            ],
            [
                "4",
                "14"
            ],
            [
                "5",
                "14"
            ],
            [
                "17",
                "18"
            ],
            [
                "6",
                "20"
            ],
            [
                "18",
                "24"
            ]
        ],
        "13": [
            [
                "2",
                "4"
            ],
            [
                "2",
                "13"
            ],
            [
                "2",
                "15"
            ],
            [
                "7",
                "13"
            ],
            [
                "1",
                "10"
            ],
            [
                "1",
                "19"
            ],
            [
                "4",
                "6"
            ],
            [
                "3",
                "7"
            ],
            [
                "8",
                "18"
            ],
            [
                "1",
                "12"
            ],
            [
                "22",
                "23"
            ],
            [
                "7",
                "23"
            ],
            [
                "5",
                "17"
            ],
            [
                "16",
                "24"
            ],
            [
                "5",
                "22"
            ],
            [
                "12",
                "16"
            ],
            [
                "6",
                "17"
            ],
            [
                "7",
                "18"
            ],
            [
                "8",
                "21"
            ],
            [
                "13",
                "14"
            ],
            [
                "11",
                "19"
            ],
            [
                "12",
                "20"
            ],
            [
                "3",
                "15"
            ],
            [
                "1",
                "11"
            ],
            [
                "5",
                "18"
            ],
            [
                "18",
                "19"
            ],
            [
                "6",
                "13"
            ],
            [
                "19",
                "21"
            ],
            [
                "3",
                "6"
            ],
            [
                "2",
                "7"
            ],
            [
                "2",
                "20"
            ],
            [
                "4",
                "16"
            ],
            [
                "9",
                "24"
            ],
            [
                "12",
                "15"
            ],
            [
                "1",
                "16"
            ],
            [
                "10",
                "17"
            ],
            [
                "11",
                "12"
            ],
            [
                "14",
                "17"
            ],
            [
                "23",
                "24"
            ],
            [
                "11",
                "21"
            ],
            [
                "2",
                "14"
            ],
            [
                "9",
                "19"
            ],
            [
                "2",
                "6"
            ],
            [
                "4",
                "22"
            ],
            [
                "4",
                "14"
            ],
            [
                "5",
                "14"
            ],
            [
                "17",
                "18"
            ],
            [
                "6",
                "20"
            ],
            [
                "18",
                "24"
            ]
        ],
        "14": [
            [
                "2",
                "4"
            ],
            [
                "2",
                "13"
            ],
            [
                "2",
                "15"
            ],
            [
                "7",
                "13"
            ],
            [
                "1",
                "10"
            ],
            [
                "1",
                "19"
            ],
            [
                "4",
                "6"
            ],
            [
                "3",
                "7"
            ],
            [
                "8",
                "18"
            ],
            [
                "1",
                "12"
            ],
            [
                "22",
                "23"
            ],
            [
                "7",
                "23"
            ],
            [
                "5",
                "17"
            ],
            [
                "16",
                "24"
            ],
            [
                "5",
                "22"
            ],
            [
                "12",
                "16"
            ],
            [
                "6",
                "17"
            ],
            [
                "7",
                "18"
            ],
            [
                "8",
                "21"
            ],
            [
                "13",
                "14"
            ],
            [
                "11",
                "19"
            ],
            [
                "12",
                "20"
            ],
            [
                "3",
                "15"
            ],
            [
                "1",
                "11"
            ],
            [
                "5",
                "18"
            ],
            [
                "18",
                "19"
            ],
            [
                "6",
                "13"
            ],
            [
                "19",
                "21"
            ],
            [
                "3",
                "6"
            ],
            [
                "2",
                "7"
            ],
            [
                "2",
                "20"
            ],
            [
                "4",
                "16"
            ],
            [
                "9",
                "24"
            ],
            [
                "12",
                "15"
            ],
            [
                "1",
                "16"
            ],
            [
                "10",
                "17"
            ],
            [
                "11",
                "12"
            ],
            [
                "14",
                "17"
            ],
            [
                "23",
                "24"
            ],
            [
                "11",
                "21"
            ],
            [
                "2",
                "14"
            ],
            [
                "9",
                "19"
            ],
            [
                "2",
                "6"
            ],
            [
                "4",
                "22"
            ],
            [
                "4",
                "14"
            ],
            [
                "5",
                "14"
            ],
            [
                "17",
                "18"
            ],
            [
                "6",
                "20"
            ],
            [
                "18",
                "24"
            ]
        ],
        "15": [
            [
                "2",
                "4"
            ],
            [
                "2",
                "13"
            ],
            [
                "2",
                "15"
            ],
            [
                "7",
                "13"
            ],
            [
                "1",
                "10"
            ],
            [
                "1",
                "19"
            ],
            [
                "4",
                "6"
            ],
            [
                "3",
                "7"
            ],
            [
                "8",
                "18"
            ],
            [
                "1",
                "12"
            ],
            [
                "22",
                "23"
            ],
            [
                "7",
                "23"
            ],
            [
                "5",
                "17"
            ],
            [
                "16",
                "24"
            ],
            [
                "5",
                "22"
            ],
            [
                "12",
                "16"
            ],
            [
                "6",
                "17"
            ],
            [
                "7",
                "18"
            ],
            [
                "8",
                "21"
            ],
            [
                "13",
                "14"
            ],
            [
                "11",
                "19"
            ],
            [
                "12",
                "20"
            ],
            [
                "3",
                "15"
            ],
            [
                "1",
                "11"
            ],
            [
                "5",
                "18"
            ],
            [
                "18",
                "19"
            ],
            [
                "6",
                "13"
            ],
            [
                "19",
                "21"
            ],
            [
                "3",
                "6"
            ],
            [
                "2",
                "7"
            ],
            [
                "2",
                "20"
            ],
            [
                "4",
                "16"
            ],
            [
                "9",
                "24"
            ],
            [
                "12",
                "15"
            ],
            [
                "1",
                "16"
            ],
            [
                "10",
                "17"
            ],
            [
                "11",
                "12"
            ],
            [
                "14",
                "17"
            ],
            [
                "23",
                "24"
            ],
            [
                "11",
                "21"
            ],
            [
                "2",
                "14"
            ],
            [
                "9",
                "19"
            ],
            [
                "2",
                "6"
            ],
            [
                "4",
                "22"
            ],
            [
                "4",
                "14"
            ],
            [
                "5",
                "14"
            ],
            [
                "17",
                "18"
            ],
            [
                "6",
                "20"
            ],
            [
                "18",
                "24"
            ]
        ],
        "16": [
            [
                "2",
                "4"
            ],
            [
                "2",
                "13"
            ],
            [
                "2",
                "15"
            ],
            [
                "7",
                "13"
            ],
            [
                "1",
                "10"
            ],
            [
                "1",
                "19"
            ],
            [
                "4",
                "6"
            ],
            [
                "3",
                "7"
            ],
            [
                "8",
                "18"
            ],
            [
                "1",
                "12"
            ],
            [
                "22",
                "23"
            ],
            [
                "7",
                "23"
            ],
            [
                "5",
                "17"
            ],
            [
                "16",
                "24"
            ],
            [
                "5",
                "22"
            ],
            [
                "12",
                "16"
            ],
            [
                "6",
                "17"
            ],
            [
                "7",
                "18"
            ],
            [
                "8",
                "21"
            ],
            [
                "13",
                "14"
            ],
            [
                "11",
                "19"
            ],
            [
                "12",
                "20"
            ],
            [
                "3",
                "15"
            ],
            [
                "1",
                "11"
            ],
            [
                "5",
                "18"
            ],
            [
                "18",
                "19"
            ],
            [
                "6",
                "13"
            ],
            [
                "19",
                "21"
            ],
            [
                "3",
                "6"
            ],
            [
                "2",
                "7"
            ],
            [
                "2",
                "20"
            ],
            [
                "4",
                "16"
            ],
            [
                "9",
                "24"
            ],
            [
                "12",
                "15"
            ],
            [
                "1",
                "16"
            ],
            [
                "10",
                "17"
            ],
            [
                "11",
                "12"
            ],
            [
                "14",
                "17"
            ],
            [
                "23",
                "24"
            ],
            [
                "11",
                "21"
            ],
            [
                "2",
                "14"
            ],
            [
                "9",
                "19"
            ],
            [
                "2",
                "6"
            ],
            [
                "4",
                "22"
            ],
            [
                "4",
                "14"
            ],
            [
                "5",
                "14"
            ],
            [
                "17",
                "18"
            ],
            [
                "6",
                "20"
            ],
            [
                "18",
                "24"
            ]
        ],
        "17": [
            [
                "2",
                "4"
            ],
            [
                "2",
                "13"
            ],
            [
                "2",
                "15"
            ],
            [
                "7",
                "13"
            ],
            [
                "1",
                "10"
            ],
            [
                "1",
                "19"
            ],
            [
                "4",
                "6"
            ],
            [
                "3",
                "7"
            ],
            [
                "8",
                "18"
            ],
            [
                "1",
                "12"
            ],
            [
                "22",
                "23"
            ],
            [
                "7",
                "23"
            ],
            [
                "5",
                "17"
            ],
            [
                "16",
                "24"
            ],
            [
                "5",
                "22"
            ],
            [
                "12",
                "16"
            ],
            [
                "6",
                "17"
            ],
            [
                "7",
                "18"
            ],
            [
                "8",
                "21"
            ],
            [
                "13",
                "14"
            ],
            [
                "11",
                "19"
            ],
            [
                "12",
                "20"
            ],
            [
                "3",
                "15"
            ],
            [
                "1",
                "11"
            ],
            [
                "5",
                "18"
            ],
            [
                "18",
                "19"
            ],
            [
                "6",
                "13"
            ],
            [
                "19",
                "21"
            ],
            [
                "3",
                "6"
            ],
            [
                "2",
                "7"
            ],
            [
                "2",
                "20"
            ],
            [
                "4",
                "16"
            ],
            [
                "9",
                "24"
            ],
            [
                "12",
                "15"
            ],
            [
                "1",
                "16"
            ],
            [
                "10",
                "17"
            ],
            [
                "11",
                "12"
            ],
            [
                "14",
                "17"
            ],
            [
                "23",
                "24"
            ],
            [
                "11",
                "21"
            ],
            [
                "2",
                "14"
            ],
            [
                "9",
                "19"
            ],
            [
                "2",
                "6"
            ],
            [
                "4",
                "22"
            ],
            [
                "4",
                "14"
            ],
            [
                "5",
                "14"
            ],
            [
                "17",
                "18"
            ],
            [
                "6",
                "20"
            ],
            [
                "18",
                "24"
            ]
        ],
        "18": [
            [
                "2",
                "4"
            ],
            [
                "2",
                "13"
            ],
            [
                "2",
                "15"
            ],
            [
                "7",
                "13"
            ],
            [
                "1",
                "10"
            ],
            [
                "1",
                "19"
            ],
            [
                "4",
                "6"
            ],
            [
                "3",
                "7"
            ],
            [
                "8",
                "18"
            ],
            [
                "1",
                "12"
            ],
            [
                "22",
                "23"
            ],
            [
                "7",
                "23"
            ],
            [
                "5",
                "17"
            ],
            [
                "16",
                "24"
            ],
            [
                "5",
                "22"
            ],
            [
                "12",
                "16"
            ],
            [
                "6",
                "17"
            ],
            [
                "7",
                "18"
            ],
            [
                "8",
                "21"
            ],
            [
                "13",
                "14"
            ],
            [
                "11",
                "19"
            ],
            [
                "12",
                "20"
            ],
            [
                "3",
                "15"
            ],
            [
                "1",
                "11"
            ],
            [
                "5",
                "18"
            ],
            [
                "18",
                "19"
            ],
            [
                "6",
                "13"
            ],
            [
                "19",
                "21"
            ],
            [
                "3",
                "6"
            ],
            [
                "2",
                "7"
            ],
            [
                "2",
                "20"
            ],
            [
                "4",
                "16"
            ],
            [
                "9",
                "24"
            ],
            [
                "12",
                "15"
            ],
            [
                "1",
                "16"
            ],
            [
                "10",
                "17"
            ],
            [
                "11",
                "12"
            ],
            [
                "14",
                "17"
            ],
            [
                "23",
                "24"
            ],
            [
                "11",
                "21"
            ],
            [
                "2",
                "14"
            ],
            [
                "9",
                "19"
            ],
            [
                "2",
                "6"
            ],
            [
                "4",
                "22"
            ],
            [
                "4",
                "14"
            ],
            [
                "5",
                "14"
            ],
            [
                "17",
                "18"
            ],
            [
                "6",
                "20"
            ],
            [
                "18",
                "24"
            ]
        ],
        "19": [
            [
                "2",
                "4"
            ],
            [
                "2",
                "13"
            ],
            [
                "2",
                "15"
            ],
            [
                "7",
                "13"
            ],
            [
                "1",
                "10"
            ],
            [
                "1",
                "19"
            ],
            [
                "4",
                "6"
            ],
            [
                "3",
                "7"
            ],
            [
                "8",
                "18"
            ],
            [
                "1",
                "12"
            ],
            [
                "22",
                "23"
            ],
            [
                "7",
                "23"
            ],
            [
                "5",
                "17"
            ],
            [
                "16",
                "24"
            ],
            [
                "5",
                "22"
            ],
            [
                "12",
                "16"
            ],
            [
                "6",
                "17"
            ],
            [
                "7",
                "18"
            ],
            [
                "8",
                "21"
            ],
            [
                "13",
                "14"
            ],
            [
                "11",
                "19"
            ],
            [
                "12",
                "20"
            ],
            [
                "3",
                "15"
            ],
            [
                "1",
                "11"
            ],
            [
                "5",
                "18"
            ],
            [
                "18",
                "19"
            ],
            [
                "6",
                "13"
            ],
            [
                "19",
                "21"
            ],
            [
                "3",
                "6"
            ],
            [
                "2",
                "7"
            ],
            [
                "2",
                "20"
            ],
            [
                "4",
                "16"
            ],
            [
                "9",
                "24"
            ],
            [
                "12",
                "15"
            ],
            [
                "1",
                "16"
            ],
            [
                "10",
                "17"
            ],
            [
                "11",
                "12"
            ],
            [
                "14",
                "17"
            ],
            [
                "23",
                "24"
            ],
            [
                "11",
                "21"
            ],
            [
                "2",
                "14"
            ],
            [
                "9",
                "19"
            ],
            [
                "2",
                "6"
            ],
            [
                "4",
                "22"
            ],
            [
                "4",
                "14"
            ],
            [
                "5",
                "14"
            ],
            [
                "17",
                "18"
            ],
            [
                "6",
                "20"
            ],
            [
                "18",
                "24"
            ]
        ],
        "20": [
            [
                "2",
                "4"
            ],
            [
                "2",
                "13"
            ],
            [
                "2",
                "15"
            ],
            [
                "7",
                "13"
            ],
            [
                "1",
                "10"
            ],
            [
                "1",
                "19"
            ],
            [
                "4",
                "6"
            ],
            [
                "3",
                "7"
            ],
            [
                "8",
                "18"
            ],
            [
                "1",
                "12"
            ],
            [
                "22",
                "23"
            ],
            [
                "7",
                "23"
            ],
            [
                "5",
                "17"
            ],
            [
                "16",
                "24"
            ],
            [
                "5",
                "22"
            ],
            [
                "12",
                "16"
            ],
            [
                "6",
                "17"
            ],
            [
                "7",
                "18"
            ],
            [
                "8",
                "21"
            ],
            [
                "13",
                "14"
            ],
            [
                "11",
                "19"
            ],
            [
                "12",
                "20"
            ],
            [
                "3",
                "15"
            ],
            [
                "1",
                "11"
            ],
            [
                "5",
                "18"
            ],
            [
                "18",
                "19"
            ],
            [
                "6",
                "13"
            ],
            [
                "19",
                "21"
            ],
            [
                "3",
                "6"
            ],
            [
                "2",
                "7"
            ],
            [
                "2",
                "20"
            ],
            [
                "4",
                "16"
            ],
            [
                "9",
                "24"
            ],
            [
                "12",
                "15"
            ],
            [
                "1",
                "16"
            ],
            [
                "10",
                "17"
            ],
            [
                "11",
                "12"
            ],
            [
                "14",
                "17"
            ],
            [
                "23",
                "24"
            ],
            [
                "11",
                "21"
            ],
            [
                "2",
                "14"
            ],
            [
                "9",
                "19"
            ],
            [
                "2",
                "6"
            ],
            [
                "4",
                "22"
            ],
            [
                "4",
                "14"
            ],
            [
                "5",
                "14"
            ],
            [
                "17",
                "18"
            ],
            [
                "6",
                "20"
            ],
            [
                "18",
                "24"
            ]
        ],
        "21": [
            [
                "2",
                "4"
            ],
            [
                "2",
                "13"
            ],
            [
                "2",
                "15"
            ],
            [
                "7",
                "13"
            ],
            [
                "1",
                "10"
            ],
            [
                "1",
                "19"
            ],
            [
                "4",
                "6"
            ],
            [
                "3",
                "7"
            ],
            [
                "8",
                "18"
            ],
            [
                "1",
                "12"
            ],
            [
                "22",
                "23"
            ],
            [
                "7",
                "23"
            ],
            [
                "5",
                "17"
            ],
            [
                "16",
                "24"
            ],
            [
                "5",
                "22"
            ],
            [
                "12",
                "16"
            ],
            [
                "6",
                "17"
            ],
            [
                "7",
                "18"
            ],
            [
                "8",
                "21"
            ],
            [
                "13",
                "14"
            ],
            [
                "11",
                "19"
            ],
            [
                "12",
                "20"
            ],
            [
                "3",
                "15"
            ],
            [
                "1",
                "11"
            ],
            [
                "5",
                "18"
            ],
            [
                "18",
                "19"
            ],
            [
                "6",
                "13"
            ],
            [
                "19",
                "21"
            ],
            [
                "3",
                "6"
            ],
            [
                "2",
                "7"
            ],
            [
                "2",
                "20"
            ],
            [
                "4",
                "16"
            ],
            [
                "9",
                "24"
            ],
            [
                "12",
                "15"
            ],
            [
                "1",
                "16"
            ],
            [
                "10",
                "17"
            ],
            [
                "11",
                "12"
            ],
            [
                "14",
                "17"
            ],
            [
                "23",
                "24"
            ],
            [
                "11",
                "21"
            ],
            [
                "2",
                "14"
            ],
            [
                "9",
                "19"
            ],
            [
                "2",
                "6"
            ],
            [
                "4",
                "22"
            ],
            [
                "4",
                "14"
            ],
            [
                "5",
                "14"
            ],
            [
                "17",
                "18"
            ],
            [
                "6",
                "20"
            ],
            [
                "18",
                "24"
            ]
        ],
        "22": [
            [
                "2",
                "4"
            ],
            [
                "2",
                "13"
            ],
            [
                "2",
                "15"
            ],
            [
                "7",
                "13"
            ],
            [
                "1",
                "10"
            ],
            [
                "1",
                "19"
            ],
            [
                "4",
                "6"
            ],
            [
                "3",
                "7"
            ],
            [
                "8",
                "18"
            ],
            [
                "1",
                "12"
            ],
            [
                "22",
                "23"
            ],
            [
                "7",
                "23"
            ],
            [
                "5",
                "17"
            ],
            [
                "16",
                "24"
            ],
            [
                "5",
                "22"
            ],
            [
                "12",
                "16"
            ],
            [
                "6",
                "17"
            ],
            [
                "7",
                "18"
            ],
            [
                "8",
                "21"
            ],
            [
                "13",
                "14"
            ],
            [
                "11",
                "19"
            ],
            [
                "12",
                "20"
            ],
            [
                "3",
                "15"
            ],
            [
                "1",
                "11"
            ],
            [
                "5",
                "18"
            ],
            [
                "18",
                "19"
            ],
            [
                "6",
                "13"
            ],
            [
                "19",
                "21"
            ],
            [
                "3",
                "6"
            ],
            [
                "2",
                "7"
            ],
            [
                "2",
                "20"
            ],
            [
                "4",
                "16"
            ],
            [
                "9",
                "24"
            ],
            [
                "12",
                "15"
            ],
            [
                "1",
                "16"
            ],
            [
                "10",
                "17"
            ],
            [
                "11",
                "12"
            ],
            [
                "14",
                "17"
            ],
            [
                "23",
                "24"
            ],
            [
                "11",
                "21"
            ],
            [
                "2",
                "14"
            ],
            [
                "9",
                "19"
            ],
            [
                "2",
                "6"
            ],
            [
                "4",
                "22"
            ],
            [
                "4",
                "14"
            ],
            [
                "5",
                "14"
            ],
            [
                "17",
                "18"
            ],
            [
                "6",
                "20"
            ],
            [
                "18",
                "24"
            ]
        ],
        "23": [
            [
                "2",
                "4"
            ],
            [
                "2",
                "13"
            ],
            [
                "2",
                "15"
            ],
            [
                "7",
                "13"
            ],
            [
                "1",
                "10"
            ],
            [
                "1",
                "19"
            ],
            [
                "4",
                "6"
            ],
            [
                "3",
                "7"
            ],
            [
                "8",
                "18"
            ],
            [
                "1",
                "12"
            ],
            [
                "22",
                "23"
            ],
            [
                "7",
                "23"
            ],
            [
                "5",
                "17"
            ],
            [
                "16",
                "24"
            ],
            [
                "5",
                "22"
            ],
            [
                "12",
                "16"
            ],
            [
                "6",
                "17"
            ],
            [
                "7",
                "18"
            ],
            [
                "8",
                "21"
            ],
            [
                "13",
                "14"
            ],
            [
                "11",
                "19"
            ],
            [
                "12",
                "20"
            ],
            [
                "3",
                "15"
            ],
            [
                "1",
                "11"
            ],
            [
                "5",
                "18"
            ],
            [
                "18",
                "19"
            ],
            [
                "6",
                "13"
            ],
            [
                "19",
                "21"
            ],
            [
                "3",
                "6"
            ],
            [
                "2",
                "7"
            ],
            [
                "2",
                "20"
            ],
            [
                "4",
                "16"
            ],
            [
                "9",
                "24"
            ],
            [
                "12",
                "15"
            ],
            [
                "1",
                "16"
            ],
            [
                "10",
                "17"
            ],
            [
                "11",
                "12"
            ],
            [
                "14",
                "17"
            ],
            [
                "23",
                "24"
            ],
            [
                "11",
                "21"
            ],
            [
                "2",
                "14"
            ],
            [
                "9",
                "19"
            ],
            [
                "2",
                "6"
            ],
            [
                "4",
                "22"
            ],
            [
                "4",
                "14"
            ],
            [
                "5",
                "14"
            ],
            [
                "17",
                "18"
            ],
            [
                "6",
                "20"
            ],
            [
                "18",
                "24"
            ]
        ],
        "24": [
            [
                "2",
                "4"
            ],
            [
                "2",
                "13"
            ],
            [
                "2",
                "15"
            ],
            [
                "7",
                "13"
            ],
            [
                "1",
                "10"
            ],
            [
                "1",
                "19"
            ],
            [
                "4",
                "6"
            ],
            [
                "3",
                "7"
            ],
            [
                "8",
                "18"
            ],
            [
                "1",
                "12"
            ],
            [
                "22",
                "23"
            ],
            [
                "7",
                "23"
            ],
            [
                "5",
                "17"
            ],
            [
                "16",
                "24"
            ],
            [
                "5",
                "22"
            ],
            [
                "12",
                "16"
            ],
            [
                "6",
                "17"
            ],
            [
                "7",
                "18"
            ],
            [
                "8",
                "21"
            ],
            [
                "13",
                "14"
            ],
            [
                "11",
                "19"
            ],
            [
                "12",
                "20"
            ],
            [
                "3",
                "15"
            ],
            [
                "1",
                "11"
            ],
            [
                "5",
                "18"
            ],
            [
                "18",
                "19"
            ],
            [
                "6",
                "13"
            ],
            [
                "19",
                "21"
            ],
            [
                "3",
                "6"
            ],
            [
                "2",
                "7"
            ],
            [
                "2",
                "20"
            ],
            [
                "4",
                "16"
            ],
            [
                "9",
                "24"
            ],
            [
                "12",
                "15"
            ],
            [
                "1",
                "16"
            ],
            [
                "10",
                "17"
            ],
            [
                "11",
                "12"
            ],
            [
                "14",
                "17"
            ],
            [
                "23",
                "24"
            ],
            [
                "11",
                "21"
            ],
            [
                "2",
                "14"
            ],
            [
                "9",
                "19"
            ],
            [
                "2",
                "6"
            ],
            [
                "4",
                "22"
            ],
            [
                "4",
                "14"
            ],
            [
                "5",
                "14"
            ],
            [
                "17",
                "18"
            ],
            [
                "6",
                "20"
            ],
            [
                "18",
                "24"
            ]
        ]
    }
}